fastapi_simple_security/__init__.py
fastapi_simple_security/_security_secret.py
fastapi_simple_security/_sqlite_access.py
fastapi_simple_security/endpoints.py
fastapi_simple_security/security_api_key.py
fastapi_simple_security/test.py
fastapi_simple_security_sql_server-0.1.dist-info/METADATA
fastapi_simple_security_sql_server-0.1.dist-info/WHEEL
fastapi_simple_security_sql_server-0.1.dist-info/top_level.txt
fastapi_simple_security_sql_server-0.1.dist-info/RECORD
