Metadata-Version: 2.1
Name: fastapi-simple-security-sql-server
Version: 0.1
Summary: API key based security package for FastAPI, focused on simplicity of use
Home-page: https://github.com/karmalegend/fastapi_simple_security
Author: Bart Ouwerkerk
Author-email: b.ouwerkerk@mvgm.nl
License: MIT
Platform: UNKNOWN
Classifier: Development Status :: 1 - Planning
Classifier: Intended Audience :: Science/Research
Classifier: License :: OSI Approved :: BSD License
Classifier: Operating System :: POSIX :: Linux
Classifier: Programming Language :: Python :: 2
Classifier: Programming Language :: Python :: 2.7
Classifier: Programming Language :: Python :: 3
Classifier: Programming Language :: Python :: 3.4
Classifier: Programming Language :: Python :: 3.5
Requires-Dist: fastapi
Requires-Dist: pyodbc
